{
  "version": 1,
  "projects": {
    "resume-builder": {
      "projectType": "application",
      "schematics": {
        "@schematics/angular:component": {
          "style": "scss"
        }
      },
      "root": "apps/resume-builder",
      "sourceRoot": "apps/resume-builder/src",
      "prefix": "resb",
      "architect": {
        "build": {
          "builder": "@angular-builders/custom-webpack:browser",
          "options": {
            "customWebpackConfig": {
              "path": "apps/resume-builder/webpack.config.js"
            },
            "outputPath": "dist/apps/resume-builder",
            "index": "apps/resume-builder/src/index.html",
            "main": "apps/resume-builder/src/main.ts",
            "polyfills": "apps/resume-builder/src/polyfills.ts",
            "tsConfig": "apps/resume-builder/tsconfig.app.json",
            "aot": true,
            "assets": [
              "apps/resume-builder/src/favicon.ico",
              "apps/resume-builder/src/assets"
            ],
            "styles": [
              "apps/resume-builder/src/styles.scss"
            ],
            "scripts": []
          },
          "configurations": {
            "production": {
              "fileReplacements": [
                {
                  "replace": "apps/resume-builder/src/environments/environment.ts",
                  "with": "apps/resume-builder/src/environments/environment.prod.ts"
                }
              ],
              "optimization": true,
              "outputHashing": "all",
              "sourceMap": false,
              "extractCss": true,
              "namedChunks": false,
              "extractLicenses": true,
              "vendorChunk": false,
              "buildOptimizer": true,
              "budgets": [
                {
                  "type": "initial",
                  "maximumWarning": "2mb",
                  "maximumError": "5mb"
                },
                {
                  "type": "anyComponentStyle",
                  "maximumWarning": "6kb",
                  "maximumError": "10kb"
                }
              ]
            }
          }
        },
        "serve": {
          "builder": "@angular-builders/custom-webpack:dev-server",
          "options": {
            "browserTarget": "resume-builder:build",
            "proxyConfig": "apps/resume-builder/proxy.conf.json"
          },
          "configurations": {
            "production": {
              "browserTarget": "resume-builder:build:production"
            }
          }
        },
        "extract-i18n": {
          "builder": "@angular-devkit/build-angular:extract-i18n",
          "options": {
            "browserTarget": "resume-builder:build"
          }
        },
        "lint": {
          "builder": "@angular-devkit/build-angular:tslint",
          "options": {
            "tsConfig": [
              "apps/resume-builder/tsconfig.app.json",
              "apps/resume-builder/tsconfig.spec.json"
            ],
            "exclude": [
              "**/node_modules/**",
              "!apps/resume-builder/**/*"
            ]
          }
        },
        "test": {
          "builder": "@nrwl/jest:jest",
          "options": {
            "jestConfig": "apps/resume-builder/jest.config.js",
            "passWithNoTests": true
          },
          "outputs": [
            "coverage/apps/resume-builder"
          ]
        }
      }
    },
    "resume-builder-e2e": {
      "root": "apps/resume-builder-e2e",
      "sourceRoot": "apps/resume-builder-e2e/src",
      "projectType": "application",
      "architect": {
        "e2e": {
          "builder": "@nrwl/cypress:cypress",
          "options": {
            "cypressConfig": "apps/resume-builder-e2e/cypress.json",
            "tsConfig": "apps/resume-builder-e2e/tsconfig.e2e.json",
            "devServerTarget": "resume-builder:serve"
          },
          "configurations": {
            "production": {
              "devServerTarget": "resume-builder:serve:production"
            }
          }
        },
        "lint": {
          "builder": "@angular-devkit/build-angular:tslint",
          "options": {
            "tsConfig": [
              "apps/resume-builder-e2e/tsconfig.e2e.json"
            ],
            "exclude": [
              "**/node_modules/**",
              "!apps/resume-builder-e2e/**/*"
            ]
          }
        }
      }
    },
    "resume-builder-api": {
      "root": "apps/resume-builder-api",
      "sourceRoot": "apps/resume-builder-api/src",
      "projectType": "application",
      "prefix": "resume-builder-api",
      "schematics": {},
      "architect": {
        "build": {
          "builder": "@nrwl/node:build",
          "options": {
            "outputPath": "dist/apps/resume-builder-api",
            "main": "apps/resume-builder-api/src/main.ts",
            "tsConfig": "apps/resume-builder-api/tsconfig.app.json",
            "assets": [
              "apps/resume-builder-api/src/assets"
            ]
          },
          "configurations": {
            "production": {
              "optimization": true,
              "extractLicenses": true,
              "inspect": false,
              "fileReplacements": [
                {
                  "replace": "apps/resume-builder-api/src/environments/environment.ts",
                  "with": "apps/resume-builder-api/src/environments/environment.prod.ts"
                }
              ]
            }
          },
          "outputs": [
            "{options.outputPath}"
          ]
        },
        "serve": {
          "builder": "@nrwl/node:execute",
          "options": {
            "buildTarget": "resume-builder-api:build"
          }
        },
        "lint": {
          "builder": "@nrwl/linter:lint",
          "options": {
            "linter": "eslint",
            "tsConfig": [
              "apps/resume-builder-api/tsconfig.app.json",
              "apps/resume-builder-api/tsconfig.spec.json"
            ],
            "exclude": [
              "**/node_modules/**",
              "!apps/resume-builder-api/**/*"
            ]
          }
        },
        "test": {
          "builder": "@nrwl/jest:jest",
          "options": {
            "jestConfig": "apps/resume-builder-api/jest.config.js",
            "passWithNoTests": true
          },
          "outputs": [
            "coverage/apps/resume-builder-api"
          ]
        }
      }
    },
    "resume-builder-resume-shell-resume": {
      "projectType": "library",
      "root": "libs/resume-builder/resume/shell-resume",
      "sourceRoot": "libs/resume-builder/resume/shell-resume/src",
      "prefix": "coderisland",
      "architect": {
        "lint": {
          "builder": "@angular-devkit/build-angular:tslint",
          "options": {
            "tsConfig": [
              "libs/resume-builder/resume/shell-resume/tsconfig.lib.json",
              "libs/resume-builder/resume/shell-resume/tsconfig.spec.json"
            ],
            "exclude": [
              "**/node_modules/**",
              "!libs/resume-builder/resume/shell-resume/**/*"
            ]
          }
        },
        "test": {
          "builder": "@nrwl/jest:jest",
          "options": {
            "jestConfig": "libs/resume-builder/resume/shell-resume/jest.config.js",
            "passWithNoTests": true
          },
          "outputs": [
            "coverage/libs/resume-builder/resume/shell-resume"
          ]
        }
      },
      "schematics": {
        "@schematics/angular:component": {
          "style": "scss"
        }
      }
    },
    "resume-builder-resume-feature-resume-list": {
      "projectType": "library",
      "root": "libs/resume-builder/resume/feature-resume-list",
      "sourceRoot": "libs/resume-builder/resume/feature-resume-list/src",
      "prefix": "coderisland",
      "architect": {
        "lint": {
          "builder": "@angular-devkit/build-angular:tslint",
          "options": {
            "tsConfig": [
              "libs/resume-builder/resume/feature-resume-list/tsconfig.lib.json",
              "libs/resume-builder/resume/feature-resume-list/tsconfig.spec.json"
            ],
            "exclude": [
              "**/node_modules/**",
              "!libs/resume-builder/resume/feature-resume-list/**/*"
            ]
          }
        },
        "test": {
          "builder": "@nrwl/jest:jest",
          "options": {
            "jestConfig": "libs/resume-builder/resume/feature-resume-list/jest.config.js",
            "passWithNoTests": true
          },
          "outputs": [
            "coverage/libs/resume-builder/resume/feature-resume-list"
          ]
        }
      },
      "schematics": {
        "@schematics/angular:component": {
          "style": "scss"
        }
      }
    },
    "resume-builder-resume-feature-resume-details": {
      "projectType": "library",
      "root": "libs/resume-builder/resume/feature-resume-details",
      "sourceRoot": "libs/resume-builder/resume/feature-resume-details/src",
      "prefix": "coderisland",
      "architect": {
        "lint": {
          "builder": "@angular-devkit/build-angular:tslint",
          "options": {
            "tsConfig": [
              "libs/resume-builder/resume/feature-resume-details/tsconfig.lib.json",
              "libs/resume-builder/resume/feature-resume-details/tsconfig.spec.json"
            ],
            "exclude": [
              "**/node_modules/**",
              "!libs/resume-builder/resume/feature-resume-details/**/*"
            ]
          }
        },
        "test": {
          "builder": "@nrwl/jest:jest",
          "options": {
            "jestConfig": "libs/resume-builder/resume/feature-resume-details/jest.config.js",
            "passWithNoTests": true
          },
          "outputs": [
            "coverage/libs/resume-builder/resume/feature-resume-details"
          ]
        }
      },
      "schematics": {
        "@schematics/angular:component": {
          "style": "scss"
        }
      }
    },
    "resume-builder-domain-interfaces": {
      "root": "libs/resume-builder/domain/interfaces",
      "sourceRoot": "libs/resume-builder/domain/interfaces/src",
      "projectType": "library",
      "schematics": {},
      "architect": {
        "lint": {
          "builder": "@nrwl/linter:lint",
          "options": {
            "linter": "eslint",
            "tsConfig": [
              "libs/resume-builder/domain/interfaces/tsconfig.lib.json",
              "libs/resume-builder/domain/interfaces/tsconfig.spec.json"
            ],
            "exclude": [
              "**/node_modules/**",
              "!libs/resume-builder/domain/interfaces/**/*"
            ]
          }
        },
        "test": {
          "builder": "@nrwl/jest:jest",
          "options": {
            "jestConfig": "libs/resume-builder/domain/interfaces/jest.config.js",
            "passWithNoTests": true
          },
          "outputs": [
            "coverage/libs/resume-builder/domain/interfaces"
          ]
        }
      }
    },
    "resume-builder-resume-data-access": {
      "projectType": "library",
      "root": "libs/resume-builder/resume/data-access",
      "sourceRoot": "libs/resume-builder/resume/data-access/src",
      "prefix": "coderisland",
      "architect": {
        "lint": {
          "builder": "@angular-devkit/build-angular:tslint",
          "options": {
            "tsConfig": [
              "libs/resume-builder/resume/data-access/tsconfig.lib.json",
              "libs/resume-builder/resume/data-access/tsconfig.spec.json"
            ],
            "exclude": [
              "**/node_modules/**",
              "!libs/resume-builder/resume/data-access/**/*"
            ]
          }
        },
        "test": {
          "builder": "@nrwl/jest:jest",
          "options": {
            "jestConfig": "libs/resume-builder/resume/data-access/jest.config.js",
            "passWithNoTests": true
          },
          "outputs": [
            "coverage/libs/resume-builder/resume/data-access"
          ]
        }
      },
      "schematics": {
        "@schematics/angular:component": {
          "style": "scss"
        }
      }
    },
    "shared-directives-content-host": {
      "projectType": "library",
      "root": "libs/shared/directives/content-host",
      "sourceRoot": "libs/shared/directives/content-host/src",
      "prefix": "coderisland",
      "architect": {
        "lint": {
          "builder": "@angular-devkit/build-angular:tslint",
          "options": {
            "tsConfig": [
              "libs/shared/directives/content-host/tsconfig.lib.json",
              "libs/shared/directives/content-host/tsconfig.spec.json"
            ],
            "exclude": [
              "**/node_modules/**",
              "!libs/shared/directives/content-host/**/*"
            ]
          }
        },
        "test": {
          "builder": "@nrwl/jest:jest",
          "options": {
            "jestConfig": "libs/shared/directives/content-host/jest.config.js",
            "passWithNoTests": true
          },
          "outputs": [
            "coverage/libs/shared/directives/content-host"
          ]
        }
      },
      "schematics": {
        "@schematics/angular:component": {
          "style": "scss"
        }
      }
    },
    "ui-kit-slide-in-components": {
      "projectType": "library",
      "root": "libs/ui-kit/slide-in/components",
      "sourceRoot": "libs/ui-kit/slide-in/components/src",
      "prefix": "coderisland",
      "architect": {
        "lint": {
          "builder": "@angular-devkit/build-angular:tslint",
          "options": {
            "tsConfig": [
              "libs/ui-kit/slide-in/components/tsconfig.lib.json",
              "libs/ui-kit/slide-in/components/tsconfig.spec.json"
            ],
            "exclude": [
              "**/node_modules/**",
              "!libs/ui-kit/slide-in/components/**/*"
            ]
          }
        },
        "test": {
          "builder": "@nrwl/jest:jest",
          "options": {
            "jestConfig": "libs/ui-kit/slide-in/components/jest.config.js",
            "passWithNoTests": true
          },
          "outputs": [
            "coverage/libs/ui-kit/slide-in/components"
          ]
        }
      },
      "schematics": {
        "@schematics/angular:component": {
          "style": "scss"
        }
      }
    },
    "ui-kit-slide-in-state": {
      "projectType": "library",
      "root": "libs/ui-kit/slide-in/state",
      "sourceRoot": "libs/ui-kit/slide-in/state/src",
      "prefix": "coderisland",
      "architect": {
        "lint": {
          "builder": "@angular-devkit/build-angular:tslint",
          "options": {
            "tsConfig": [
              "libs/ui-kit/slide-in/state/tsconfig.lib.json",
              "libs/ui-kit/slide-in/state/tsconfig.spec.json"
            ],
            "exclude": [
              "**/node_modules/**",
              "!libs/ui-kit/slide-in/state/**/*"
            ]
          }
        },
        "test": {
          "builder": "@nrwl/jest:jest",
          "options": {
            "jestConfig": "libs/ui-kit/slide-in/state/jest.config.js",
            "passWithNoTests": true
          },
          "outputs": [
            "coverage/libs/ui-kit/slide-in/state"
          ]
        }
      },
      "schematics": {
        "@schematics/angular:component": {
          "style": "scss"
        }
      }
    },
    "ui-kit-slide-in-service": {
      "projectType": "library",
      "root": "libs/ui-kit/slide-in/service",
      "sourceRoot": "libs/ui-kit/slide-in/service/src",
      "prefix": "coderisland",
      "architect": {
        "lint": {
          "builder": "@angular-devkit/build-angular:tslint",
          "options": {
            "tsConfig": [
              "libs/ui-kit/slide-in/service/tsconfig.lib.json",
              "libs/ui-kit/slide-in/service/tsconfig.spec.json"
            ],
            "exclude": [
              "**/node_modules/**",
              "!libs/ui-kit/slide-in/service/**/*"
            ]
          }
        },
        "test": {
          "builder": "@nrwl/jest:jest",
          "options": {
            "jestConfig": "libs/ui-kit/slide-in/service/jest.config.js",
            "passWithNoTests": true
          },
          "outputs": [
            "coverage/libs/ui-kit/slide-in/service"
          ]
        }
      },
      "schematics": {
        "@schematics/angular:component": {
          "style": "scss"
        }
      }
    },
    "resume-builder-utils-interface": {
      "root": "libs/resume-builder/utils-interface",
      "sourceRoot": "libs/resume-builder/utils-interface/src",
      "projectType": "library",
      "schematics": {},
      "architect": {
        "lint": {
          "builder": "@nrwl/linter:lint",
          "options": {
            "linter": "eslint",
            "tsConfig": [
              "libs/resume-builder/utils-interface/tsconfig.lib.json",
              "libs/resume-builder/utils-interface/tsconfig.spec.json"
            ],
            "exclude": [
              "**/node_modules/**",
              "!libs/resume-builder/utils-interface/**/*"
            ]
          }
        },
        "test": {
          "builder": "@nrwl/jest:jest",
          "options": {
            "jestConfig": "libs/resume-builder/utils-interface/jest.config.js",
            "passWithNoTests": true
          },
          "outputs": [
            "coverage/libs/resume-builder/utils-interface"
          ]
        }
      }
    },
    "ui-kit-forms-text-input": {
      "projectType": "library",
      "root": "libs/ui-kit/forms/text-input",
      "sourceRoot": "libs/ui-kit/forms/text-input/src",
      "prefix": "coderisland",
      "architect": {
        "lint": {
          "builder": "@angular-devkit/build-angular:tslint",
          "options": {
            "tsConfig": [
              "libs/ui-kit/forms/text-input/tsconfig.lib.json",
              "libs/ui-kit/forms/text-input/tsconfig.spec.json"
            ],
            "exclude": [
              "**/node_modules/**",
              "!libs/ui-kit/forms/text-input/**/*"
            ]
          }
        },
        "test": {
          "builder": "@nrwl/jest:jest",
          "options": {
            "jestConfig": "libs/ui-kit/forms/text-input/jest.config.js",
            "passWithNoTests": true
          },
          "outputs": [
            "coverage/libs/ui-kit/forms/text-input"
          ]
        }
      },
      "schematics": {
        "@schematics/angular:component": {
          "style": "scss"
        }
      }
    },
    "resume-builder-resume-feature-resume-work-experience": {
      "projectType": "library",
      "root": "libs/resume-builder/resume/feature-resume-work-experience",
      "sourceRoot": "libs/resume-builder/resume/feature-resume-work-experience/src",
      "prefix": "coderisland",
      "architect": {
        "lint": {
          "builder": "@angular-devkit/build-angular:tslint",
          "options": {
            "tsConfig": [
              "libs/resume-builder/resume/feature-resume-work-experience/tsconfig.lib.json",
              "libs/resume-builder/resume/feature-resume-work-experience/tsconfig.spec.json"
            ],
            "exclude": [
              "**/node_modules/**",
              "!libs/resume-builder/resume/feature-resume-work-experience/**/*"
            ]
          }
        },
        "test": {
          "builder": "@nrwl/jest:jest",
          "options": {
            "jestConfig": "libs/resume-builder/resume/feature-resume-work-experience/jest.config.js",
            "passWithNoTests": true
          },
          "outputs": [
            "coverage/libs/resume-builder/resume/feature-resume-work-experience"
          ]
        }
      },
      "schematics": {
        "@schematics/angular:component": {
          "style": "scss"
        }
      }
    },
    "ui-kit-forms-textarea": {
      "projectType": "library",
      "root": "libs/ui-kit/forms/textarea",
      "sourceRoot": "libs/ui-kit/forms/textarea/src",
      "prefix": "coderisland",
      "architect": {
        "lint": {
          "builder": "@angular-devkit/build-angular:tslint",
          "options": {
            "tsConfig": [
              "libs/ui-kit/forms/textarea/tsconfig.lib.json",
              "libs/ui-kit/forms/textarea/tsconfig.spec.json"
            ],
            "exclude": [
              "**/node_modules/**",
              "!libs/ui-kit/forms/textarea/**/*"
            ]
          }
        },
        "test": {
          "builder": "@nrwl/jest:jest",
          "options": {
            "jestConfig": "libs/ui-kit/forms/textarea/jest.config.js",
            "passWithNoTests": true
          },
          "outputs": [
            "coverage/libs/ui-kit/forms/textarea"
          ]
        }
      },
      "schematics": {
        "@schematics/angular:component": {
          "style": "scss"
        }
      }
    },
    "resume-builder-resume-feature-resume-education": {
      "projectType": "library",
      "root": "libs/resume-builder/resume/feature-resume-education",
      "sourceRoot": "libs/resume-builder/resume/feature-resume-education/src",
      "prefix": "coderisland",
      "architect": {
        "lint": {
          "builder": "@angular-devkit/build-angular:tslint",
          "options": {
            "tsConfig": [
              "libs/resume-builder/resume/feature-resume-education/tsconfig.lib.json",
              "libs/resume-builder/resume/feature-resume-education/tsconfig.spec.json"
            ],
            "exclude": [
              "**/node_modules/**",
              "!libs/resume-builder/resume/feature-resume-education/**/*"
            ]
          }
        },
        "test": {
          "builder": "@nrwl/jest:jest",
          "options": {
            "jestConfig": "libs/resume-builder/resume/feature-resume-education/jest.config.js",
            "passWithNoTests": true
          },
          "outputs": [
            "coverage/libs/resume-builder/resume/feature-resume-education"
          ]
        }
      },
      "schematics": {
        "@schematics/angular:component": {
          "style": "scss"
        }
      }
    },
    "resume-builder-resume-feature-resume-skills": {
      "projectType": "library",
      "root": "libs/resume-builder/resume/feature-resume-skills",
      "sourceRoot": "libs/resume-builder/resume/feature-resume-skills/src",
      "prefix": "coderisland",
      "architect": {
        "lint": {
          "builder": "@angular-devkit/build-angular:tslint",
          "options": {
            "tsConfig": [
              "libs/resume-builder/resume/feature-resume-skills/tsconfig.lib.json",
              "libs/resume-builder/resume/feature-resume-skills/tsconfig.spec.json"
            ],
            "exclude": [
              "**/node_modules/**",
              "!libs/resume-builder/resume/feature-resume-skills/**/*"
            ]
          }
        },
        "test": {
          "builder": "@nrwl/jest:jest",
          "options": {
            "jestConfig": "libs/resume-builder/resume/feature-resume-skills/jest.config.js",
            "passWithNoTests": true
          },
          "outputs": [
            "coverage/libs/resume-builder/resume/feature-resume-skills"
          ]
        }
      },
      "schematics": {
        "@schematics/angular:component": {
          "style": "scss"
        }
      }
    },
    "resume-builder-resume-feature-resume-interests": {
      "projectType": "library",
      "root": "libs/resume-builder/resume/feature-resume-interests",
      "sourceRoot": "libs/resume-builder/resume/feature-resume-interests/src",
      "prefix": "coderisland",
      "architect": {
        "lint": {
          "builder": "@angular-devkit/build-angular:tslint",
          "options": {
            "tsConfig": [
              "libs/resume-builder/resume/feature-resume-interests/tsconfig.lib.json",
              "libs/resume-builder/resume/feature-resume-interests/tsconfig.spec.json"
            ],
            "exclude": [
              "**/node_modules/**",
              "!libs/resume-builder/resume/feature-resume-interests/**/*"
            ]
          }
        },
        "test": {
          "builder": "@nrwl/jest:jest",
          "options": {
            "jestConfig": "libs/resume-builder/resume/feature-resume-interests/jest.config.js",
            "passWithNoTests": true
          },
          "outputs": [
            "coverage/libs/resume-builder/resume/feature-resume-interests"
          ]
        }
      },
      "schematics": {
        "@schematics/angular:component": {
          "style": "scss"
        }
      }
    },
    "resume-builder-resume-feature-resume-languages": {
      "projectType": "library",
      "root": "libs/resume-builder/resume/feature-resume-languages",
      "sourceRoot": "libs/resume-builder/resume/feature-resume-languages/src",
      "prefix": "coderisland",
      "architect": {
        "lint": {
          "builder": "@angular-devkit/build-angular:tslint",
          "options": {
            "tsConfig": [
              "libs/resume-builder/resume/feature-resume-languages/tsconfig.lib.json",
              "libs/resume-builder/resume/feature-resume-languages/tsconfig.spec.json"
            ],
            "exclude": [
              "**/node_modules/**",
              "!libs/resume-builder/resume/feature-resume-languages/**/*"
            ]
          }
        },
        "test": {
          "builder": "@nrwl/jest:jest",
          "options": {
            "jestConfig": "libs/resume-builder/resume/feature-resume-languages/jest.config.js",
            "passWithNoTests": true
          },
          "outputs": [
            "coverage/libs/resume-builder/resume/feature-resume-languages"
          ]
        }
      },
      "schematics": {
        "@schematics/angular:component": {
          "style": "scss"
        }
      }
    },
    "ui-kit-forms-select": {
      "projectType": "library",
      "root": "libs/ui-kit/forms/select",
      "sourceRoot": "libs/ui-kit/forms/select/src",
      "prefix": "coderisland",
      "architect": {
        "lint": {
          "builder": "@angular-devkit/build-angular:tslint",
          "options": {
            "tsConfig": [
              "libs/ui-kit/forms/select/tsconfig.lib.json",
              "libs/ui-kit/forms/select/tsconfig.spec.json"
            ],
            "exclude": [
              "**/node_modules/**",
              "!libs/ui-kit/forms/select/**/*"
            ]
          }
        },
        "test": {
          "builder": "@nrwl/jest:jest",
          "options": {
            "jestConfig": "libs/ui-kit/forms/select/jest.config.js",
            "passWithNoTests": true
          },
          "outputs": [
            "coverage/libs/ui-kit/forms/select"
          ]
        }
      },
      "schematics": {
        "@schematics/angular:component": {
          "style": "scss"
        }
      }
    },
    "resume-builder-resume-feature-resume-references": {
      "projectType": "library",
      "root": "libs/resume-builder/resume/feature-resume-references",
      "sourceRoot": "libs/resume-builder/resume/feature-resume-references/src",
      "prefix": "coderisland",
      "architect": {
        "lint": {
          "builder": "@angular-devkit/build-angular:tslint",
          "options": {
            "tsConfig": [
              "libs/resume-builder/resume/feature-resume-references/tsconfig.lib.json",
              "libs/resume-builder/resume/feature-resume-references/tsconfig.spec.json"
            ],
            "exclude": [
              "**/node_modules/**",
              "!libs/resume-builder/resume/feature-resume-references/**/*"
            ]
          }
        },
        "test": {
          "builder": "@nrwl/jest:jest",
          "options": {
            "jestConfig": "libs/resume-builder/resume/feature-resume-references/jest.config.js",
            "passWithNoTests": true
          },
          "outputs": [
            "coverage/libs/resume-builder/resume/feature-resume-references"
          ]
        }
      },
      "schematics": {
        "@schematics/angular:component": {
          "style": "scss"
        }
      }
    },
    "resume-builder-resume-feature-resume-profile": {
      "projectType": "library",
      "root": "libs/resume-builder/resume/feature-resume-profile",
      "sourceRoot": "libs/resume-builder/resume/feature-resume-profile/src",
      "prefix": "coderisland",
      "architect": {
        "lint": {
          "builder": "@angular-devkit/build-angular:tslint",
          "options": {
            "tsConfig": [
              "libs/resume-builder/resume/feature-resume-profile/tsconfig.lib.json",
              "libs/resume-builder/resume/feature-resume-profile/tsconfig.spec.json"
            ],
            "exclude": [
              "**/node_modules/**",
              "!libs/resume-builder/resume/feature-resume-profile/**/*"
            ]
          }
        },
        "test": {
          "builder": "@nrwl/jest:jest",
          "options": {
            "jestConfig": "libs/resume-builder/resume/feature-resume-profile/jest.config.js",
            "passWithNoTests": true
          },
          "outputs": [
            "coverage/libs/resume-builder/resume/feature-resume-profile"
          ]
        }
      },
      "schematics": {
        "@schematics/angular:component": {
          "style": "scss"
        }
      }
    },
    "resume-builder-resume-feature-resume-preview": {
      "projectType": "library",
      "root": "libs/resume-builder/resume/feature-resume-preview",
      "sourceRoot": "libs/resume-builder/resume/feature-resume-preview/src",
      "prefix": "coderisland",
      "architect": {
        "lint": {
          "builder": "@angular-devkit/build-angular:tslint",
          "options": {
            "tsConfig": [
              "libs/resume-builder/resume/feature-resume-preview/tsconfig.lib.json",
              "libs/resume-builder/resume/feature-resume-preview/tsconfig.spec.json"
            ],
            "exclude": [
              "**/node_modules/**",
              "!libs/resume-builder/resume/feature-resume-preview/**/*"
            ]
          }
        },
        "test": {
          "builder": "@nrwl/jest:jest",
          "options": {
            "jestConfig": "libs/resume-builder/resume/feature-resume-preview/jest.config.js",
            "passWithNoTests": true
          },
          "outputs": [
            "coverage/libs/resume-builder/resume/feature-resume-preview"
          ]
        }
      },
      "schematics": {
        "@schematics/angular:component": {
          "style": "scss"
        }
      }
    },
    "ui-kit-page-loader-services": {
      "projectType": "library",
      "root": "libs/ui-kit/page-loader/services",
      "sourceRoot": "libs/ui-kit/page-loader/services/src",
      "prefix": "coderisland",
      "architect": {
        "lint": {
          "builder": "@angular-devkit/build-angular:tslint",
          "options": {
            "tsConfig": [
              "libs/ui-kit/page-loader/services/tsconfig.lib.json",
              "libs/ui-kit/page-loader/services/tsconfig.spec.json"
            ],
            "exclude": [
              "**/node_modules/**",
              "!libs/ui-kit/page-loader/services/**/*"
            ]
          }
        },
        "test": {
          "builder": "@nrwl/jest:jest",
          "options": {
            "jestConfig": "libs/ui-kit/page-loader/services/jest.config.js",
            "passWithNoTests": true
          },
          "outputs": [
            "coverage/libs/ui-kit/page-loader/services"
          ]
        }
      },
      "schematics": {
        "@schematics/angular:component": {
          "style": "scss"
        }
      }
    },
    "ui-kit-page-loader-components": {
      "projectType": "library",
      "root": "libs/ui-kit/page-loader/components",
      "sourceRoot": "libs/ui-kit/page-loader/components/src",
      "prefix": "coderisland",
      "architect": {
        "lint": {
          "builder": "@angular-devkit/build-angular:tslint",
          "options": {
            "tsConfig": [
              "libs/ui-kit/page-loader/components/tsconfig.lib.json",
              "libs/ui-kit/page-loader/components/tsconfig.spec.json"
            ],
            "exclude": [
              "**/node_modules/**",
              "!libs/ui-kit/page-loader/components/**/*"
            ]
          }
        },
        "test": {
          "builder": "@nrwl/jest:jest",
          "options": {
            "jestConfig": "libs/ui-kit/page-loader/components/jest.config.js",
            "passWithNoTests": true
          },
          "outputs": [
            "coverage/libs/ui-kit/page-loader/components"
          ]
        }
      },
      "schematics": {
        "@schematics/angular:component": {
          "style": "scss"
        }
      }
    }
  },
  "cli": {
    "defaultCollection": "@nrwl/angular"
  },
  "schematics": {
    "@nrwl/angular:application": {
      "unitTestRunner": "jest",
      "e2eTestRunner": "cypress",
      "strict": true
    },
    "@nrwl/angular:library": {
      "unitTestRunner": "jest",
      "strict": true
    }
  },
  "defaultProject": "resume-builder"
}
